{
  "XAUUSD": {
    "bias": "NEUTRAL",
    "confidence": 4,
    "ts": "2026-05-24T15:02:45.911397+00:00",
    "price": "~2425-2435 (estimated, not explicitly stated in news)",
    "last_tier": "NONE"
  },
  "US30": {
    "bias": "NEUTRAL",
    "confidence": 5,
    "ts": "2026-05-24T15:03:12.043915+00:00",
    "price": "50,579.70",
    "last_tier": "NONE"
  },
  "NAS100": {
    "bias": "NEUTRAL",
    "confidence": 4,
    "ts": "2026-05-24T15:03:36.655555+00:00",
    "price": "29,481.64",
    "last_tier": "NONE"
  }
}